MANIFEST.in
authors.txt
changelog.txt
faq.txt
install.txt
license.txt
news.txt
readme.txt
requirements.txt
setup.py
thanks.txt
todo.txt
Camelot.egg-info/PKG-INFO
Camelot.egg-info/SOURCES.txt
Camelot.egg-info/dependency_links.txt
Camelot.egg-info/entry_points.txt
Camelot.egg-info/requires.txt
Camelot.egg-info/top_level.txt
camelot/__init__.py
camelot/admin/__init__.py
camelot/admin/application_admin.py
camelot/admin/entity_admin.py
camelot/admin/menu.py
camelot/admin/not_editable_admin.py
camelot/admin/object_admin.py
camelot/admin/section.py
camelot/admin/table.py
camelot/admin/action/__init__.py
camelot/admin/action/application_action.py
camelot/admin/action/base.py
camelot/admin/action/document_action.py
camelot/admin/action/form_action.py
camelot/admin/action/list_action.py
camelot/admin/validator/__init__.py
camelot/admin/validator/entity_validator.py
camelot/admin/validator/object_validator.py
camelot/art/__init__.py
camelot/art/close_mark.png
camelot/art/close_mark_hover.png
camelot/art/empty_document.doc
camelot/art/image_not_found.png
camelot/art/resources.py
camelot/art/splashscreen.png
camelot/art/tooltip_visualization_7x7_glow.png
camelot/art/stylesheet/black.qss
camelot/art/stylesheet/navpane3_office2007_black.qss
camelot/art/stylesheet/navpane3_office2007_blue.qss
camelot/art/stylesheet/navpane3_office2007_silver.qss
camelot/art/stylesheet/navpane_office2007_black.qss
camelot/art/stylesheet/navpane_office2007_blue.qss
camelot/art/stylesheet/navpane_office2007_silver.qss
camelot/art/stylesheet/office2007_black.qss
camelot/art/stylesheet/office2007_blue.qss
camelot/art/stylesheet/office2007_silver.qss
camelot/art/tango/16x16/actions/address-book-new.png
camelot/art/tango/16x16/actions/appointment-new.png
camelot/art/tango/16x16/actions/bookmark-new.png
camelot/art/tango/16x16/actions/contact-new.png
camelot/art/tango/16x16/actions/document-new.png
camelot/art/tango/16x16/actions/document-open.png
camelot/art/tango/16x16/actions/document-print-preview.png
camelot/art/tango/16x16/actions/document-print.png
camelot/art/tango/16x16/actions/document-properties.png
camelot/art/tango/16x16/actions/document-save-as.png
