Metadata-Version: 1.1
Name: Camelot
Version: 13.04.13-gpl-pyqt
Summary: A python GUI framework on top of Sqlalchemy and Qt, inspired by the Django admin interface. Start building desktop applications at warp speed, simply by adding some additional information to you model definition.
Home-page: http://www.python-camelot.com
Author: Conceptive Engineering
Author-email: project-camelot@conceptive.be
License: GPL, Commercial
Keywords: qt pyqt sqlalchemy elixir desktop gui framework
Platform: Linux
Platform: Windows
Platform: OS X
Classifier: Development Status :: 5 - Production/Stable
Classifier: Environment :: Win32 (MS Windows)
Classifier: Environment :: X11 Applications
Classifier: Environment :: X11 Applications :: Gnome
Classifier: Environment :: X11 Applications :: GTK
Classifier: Environment :: X11 Applications :: KDE
Classifier: Environment :: X11 Applications :: Qt
Classifier: Intended Audience :: Developers
Classifier: License :: OSI Approved :: GNU General Public License (GPL)
Classifier: License :: Other/Proprietary License
Classifier: Operating System :: MacOS :: MacOS X
Classifier: Operating System :: Microsoft :: Windows
Classifier: Operating System :: POSIX
Classifier: Programming Language :: Python
Classifier: Topic :: Database :: Front-Ends
Classifier: Topic :: Office/Business
Classifier: Topic :: Software Development :: Libraries :: Application Frameworks
